statistical_iv/__init__.py
statistical_iv/api.py
statistical_iv/helpers/__init__.py
statistical_iv/helpers/consts.py
statistical_iv-0.3.2.dist-info/LICENSE.txt
statistical_iv-0.3.2.dist-info/METADATA
statistical_iv-0.3.2.dist-info/WHEEL
statistical_iv-0.3.2.dist-info/top_level.txt
statistical_iv-0.3.2.dist-info/RECORD
