Metadata-Version: 2.1
Name: statistical-iv
Version: 0.3.2
Summary: Statistical IV: Statistical Hypothesis Testing for the Information Value (IV). Evaluation of the predictive power of features using the IV with specific thresholds for each dataset.
Home-page: https://github.com/Nicerova7/statistical_iv
Author: Nilton Rojas, Helder Rojas
Maintainer: Nilton Rojas Vales
Maintainer-email: nrojasv@uni.pe
License: MIT
Keywords: information_value,woe,data science,hypothesis test
Classifier: Development Status :: 3 - Alpha
Classifier: Intended Audience :: Developers
Classifier: Intended Audience :: Science/Research
Classifier: Intended Audience :: Information Technology
Classifier: Topic :: Scientific/Engineering
Classifier: Topic :: Software Development :: Build Tools
Classifier: License :: OSI Approved :: MIT License
Classifier: Programming Language :: Python :: 3
Classifier: Programming Language :: Python :: 3.8
Classifier: Programming Language :: Python :: 3.9
Classifier: Programming Language :: Python :: 3.10
License-File: LICENSE.txt
Requires-Dist: pandas
Requires-Dist: numpy
Requires-Dist: scipy
Requires-Dist: optbinning
